fzf/__init__.py
fzf/app.py
python_fzf-0.1.1.dist-info/LICENSE
python_fzf-0.1.1.dist-info/WHEEL
python_fzf-0.1.1.dist-info/METADATA
python_fzf-0.1.1.dist-info/RECORD
